odoo/addons/remove_odoo_enterprise/README.rst
odoo/addons/remove_odoo_enterprise/__init__.py
odoo/addons/remove_odoo_enterprise/__manifest__.py
odoo/addons/remove_odoo_enterprise/i18n/de.po
odoo/addons/remove_odoo_enterprise/i18n/hr.po
odoo/addons/remove_odoo_enterprise/i18n/it.po
odoo/addons/remove_odoo_enterprise/i18n/remove_odoo_enterprise.pot
odoo/addons/remove_odoo_enterprise/i18n/sv.po
odoo/addons/remove_odoo_enterprise/models/__init__.py
odoo/addons/remove_odoo_enterprise/models/base.py
odoo/addons/remove_odoo_enterprise/models/res_config_settings.py
odoo/addons/remove_odoo_enterprise/readme/CONTRIBUTORS.md
odoo/addons/remove_odoo_enterprise/readme/DESCRIPTION.md
odoo/addons/remove_odoo_enterprise/static/description/icon.png
odoo/addons/remove_odoo_enterprise/static/description/index.html
odoo/addons/remove_odoo_enterprise/tests/__init__.py
odoo/addons/remove_odoo_enterprise/tests/test_remove_odoo_enterprise.py
odoo_addon_remove_odoo_enterprise-19.0.1.0.0.4.dist-info/METADATA
odoo_addon_remove_odoo_enterprise-19.0.1.0.0.4.dist-info/WHEEL
odoo_addon_remove_odoo_enterprise-19.0.1.0.0.4.dist-info/top_level.txt
odoo_addon_remove_odoo_enterprise-19.0.1.0.0.4.dist-info/RECORD
