Metadata-Version: 2.1
Name: odoo-addon-remove_odoo_enterprise
Version: 19.0.1.0.0.4
Requires-Dist: odoo==19.0.*
Summary: Remove enterprise modules and setting items
Home-page: https://github.com/OCA/server-brand
License: AGPL-3
Author: Eska, Onestein, Odoo Community Association (OCA)
Author-email: support@odoo-community.org
Classifier: Programming Language :: Python
Classifier: Framework :: Odoo
Classifier: Framework :: Odoo :: 19.0
Classifier: License :: OSI Approved :: GNU Affero General Public License v3
